[{"model": "admin.logentry", "pk": 1, "fields": {"action_time": "2021-04-29T12:20:04.766Z", "user": 1, "content_type": 13, "object_id": "1", "object_repr": "portraits", "action_flag": 1, "change_message": "[{\"added\": {}}]"}}, {"model": "admin.logentry", "pk": 2, "fields": {"action_time": "2021-04-29T12:20:16.539Z", "user": 1, "content_type": 13, "object_id": "2", "object_repr": "b+w", "action_flag": 1, "change_message": "[{\"added\": {}}]"}}, {"model": "admin.logentry", "pk": 3, "fields": {"action_time": "2021-04-29T12:20:28.959Z", "user": 1, "content_type": 13, "object_id": "3", "object_repr": "collage", "action_flag": 1, "change_message": "[{\"added\": {}}]"}}, {"model": "admin.logentry", "pk": 4, "fields": {"action_time": "2021-04-29T12:20:42.637Z", "user": 1, "content_type": 13, "object_id": "4", "object_repr": "urban", "action_flag": 1, "change_message": "[{\"added\": {}}]"}}, {"model": "admin.logentry", "pk": 5, "fields": {"action_time": "2021-04-29T12:21:13.929Z", "user": 1, "content_type": 13, "object_id": "5", "object_repr": "new", "action_flag": 1, "change_message": "[{\"added\": {}}]"}}, {"model": "admin.logentry", "pk": 6, "fields": {"action_time": "2021-04-29T12:36:41.808Z", "user": 1, "content_type": 14, "object_id": "1", "object_repr": "Chesterfield", "action_flag": 1, "change_message": "[{\"added\": {}}]"}}, {"model": "admin.logentry", "pk": 7, "fields": {"action_time": "2021-04-29T12:38:09.699Z", "user": 1, "content_type": 14, "object_id": "2", "object_repr": "Sandstone", "action_flag": 1, "change_message": "[{\"added\": {}}]"}}, {"model": "admin.logentry", "pk": 8, "fields": {"action_time": "2021-04-29T12:39:45.797Z", "user": 1, "content_type": 14, "object_id": "3", "object_repr": "Lace", "action_flag": 1, "change_message": "[{\"added\": {}}]"}}, {"model": "admin.logentry", "pk": 9, "fields": {"action_time": "2021-04-29T12:41:26.737Z", "user": 1, "content_type": 14, "object_id": "4", "object_repr": "Winter", "action_flag": 1, "change_message": "[{\"added\": {}}]"}}, {"model": "admin.logentry", "pk": 10, "fields": {"action_time": "2021-04-29T12:47:12.072Z", "user": 1, "content_type": 14, "object_id": "5", "object_repr": "Mongolian", "action_flag": 1, "change_message": "[{\"added\": {}}]"}}, {"model": "admin.logentry", "pk": 11, "fields": {"action_time": "2021-04-29T12:48:06.214Z", "user": 1, "content_type": 14, "object_id": "6", "object_repr": "Rain", "action_flag": 1, "change_message": "[{\"added\": {}}]"}}, {"model": "admin.logentry", "pk": 12, "fields": {"action_time": "2021-04-29T12:49:40.301Z", "user": 1, "content_type": 14, "object_id": "7", "object_repr": "Recital", "action_flag": 1, "change_message": "[{\"added\": {}}]"}}, {"model": "admin.logentry", "pk": 13, "fields": {"action_time": "2021-04-29T12:50:36.777Z", "user": 1, "content_type": 14, "object_id": "8", "object_repr": "Martin", "action_flag": 1, "change_message": "[{\"added\": {}}]"}}, {"model": "admin.logentry", "pk": 14, "fields": {"action_time": "2021-04-29T12:51:54.249Z", "user": 1, "content_type": 14, "object_id": "9", "object_repr": "Dreams", "action_flag": 1, "change_message": "[{\"added\": {}}]"}}, {"model": "admin.logentry", "pk": 15, "fields": {"action_time": "2021-04-29T12:52:33.128Z", "user": 1, "content_type": 14, "object_id": "10", "object_repr": "Carusel", "action_flag": 1, "change_message": "[{\"added\": {}}]"}}, {"model": "admin.logentry", "pk": 16, "fields": {"action_time": "2021-04-29T12:53:50.182Z", "user": 1, "content_type": 14, "object_id": "11", "object_repr": "Middle", "action_flag": 1, "change_message": "[{\"added\": {}}]"}}, {"model": "admin.logentry", "pk": 17, "fields": {"action_time": "2021-04-29T12:54:29.913Z", "user": 1, "content_type": 14, "object_id": "12", "object_repr": "Gods", "action_flag": 1, "change_message": "[{\"added\": {}}]"}}, {"model": "admin.logentry", "pk": 18, "fields": {"action_time": "2021-04-29T12:55:59.861Z", "user": 1, "content_type": 14, "object_id": "13", "object_repr": "Shoes", "action_flag": 1, "change_message": "[{\"added\": {}}]"}}, {"model": "admin.logentry", "pk": 19, "fields": {"action_time": "2021-04-29T12:56:55.956Z", "user": 1, "content_type": 14, "object_id": "14", "object_repr": "Below", "action_flag": 1, "change_message": "[{\"added\": {}}]"}}, {"model": "admin.logentry", "pk": 20, "fields": {"action_time": "2021-04-29T13:00:28.830Z", "user": 1, "content_type": 14, "object_id": "15", "object_repr": "Burden", "action_flag": 1, "change_message": "[{\"added\": {}}]"}}, {"model": "admin.logentry", "pk": 21, "fields": {"action_time": "2021-04-29T13:01:00.111Z", "user": 1, "content_type": 14, "object_id": "16", "object_repr": "Him", "action_flag": 1, "change_message": "[{\"added\": {}}]"}}, {"model": "admin.logentry", "pk": 22, "fields": {"action_time": "2021-04-29T13:01:52.066Z", "user": 1, "content_type": 14, "object_id": "17", "object_repr": "Her", "action_flag": 1, "change_message": "[{\"added\": {}}]"}}, {"model": "admin.logentry", "pk": 23, "fields": {"action_time": "2021-04-29T13:03:50.855Z", "user": 1, "content_type": 13, "object_id": "2", "object_repr": "b_w", "action_flag": 2, "change_message": "[{\"changed\": {\"fields\": [\"Name\"]}}]"}}, {"model": "admin.logentry", "pk": 24, "fields": {"action_time": "2021-04-29T13:05:08.366Z", "user": 1, "content_type": 14, "object_id": "11", "object_repr": "Middle", "action_flag": 2, "change_message": "[{\"changed\": {\"fields\": [\"Category\"]}}]"}}, {"model": "admin.logentry", "pk": 25, "fields": {"action_time": "2021-04-29T13:06:26.640Z", "user": 1, "content_type": 14, "object_id": "18", "object_repr": "Bikes", "action_flag": 1, "change_message": "[{\"added\": {}}]"}}, {"model": "admin.logentry", "pk": 26, "fields": {"action_time": "2021-04-29T13:07:05.238Z", "user": 1, "content_type": 14, "object_id": "19", "object_repr": "Light", "action_flag": 1, "change_message": "[{\"added\": {}}]"}}, {"model": "admin.logentry", "pk": 27, "fields": {"action_time": "2021-04-29T13:08:37.806Z", "user": 1, "content_type": 13, "object_id": "5", "object_repr": "new", "action_flag": 2, "change_message": "[]"}}, {"model": "admin.logentry", "pk": 28, "fields": {"action_time": "2021-04-29T17:13:15.274Z", "user": 1, "content_type": 14, "object_id": "20", "object_repr": "Daily", "action_flag": 1, "change_message": "[{\"added\": {}}]"}}, {"model": "admin.logentry", "pk": 29, "fields": {"action_time": "2021-04-29T17:15:01.110Z", "user": 1, "content_type": 14, "object_id": "21", "object_repr": "Ekstra", "action_flag": 1, "change_message": "[{\"added\": {}}]"}}, {"model": "admin.logentry", "pk": 30, "fields": {"action_time": "2021-04-29T17:16:03.229Z", "user": 1, "content_type": 14, "object_id": "22", "object_repr": "Summer Madness One", "action_flag": 1, "change_message": "[{\"added\": {}}]"}}, {"model": "admin.logentry", "pk": 31, "fields": {"action_time": "2021-04-29T17:16:41.302Z", "user": 1, "content_type": 14, "object_id": "23", "object_repr": "Summer Madness Two", "action_flag": 1, "change_message": "[{\"added\": {}}]"}}, {"model": "admin.logentry", "pk": 32, "fields": {"action_time": "2021-04-29T17:17:18.178Z", "user": 1, "content_type": 14, "object_id": "24", "object_repr": "Summer Madness Three", "action_flag": 1, "change_message": "[{\"added\": {}}]"}}, {"model": "admin.logentry", "pk": 33, "fields": {"action_time": "2021-04-29T17:17:40.007Z", "user": 1, "content_type": 14, "object_id": "25", "object_repr": "Summer Madness Four", "action_flag": 1, "change_message": "[{\"added\": {}}]"}}, {"model": "admin.logentry", "pk": 34, "fields": {"action_time": "2021-04-29T17:18:35.700Z", "user": 1, "content_type": 14, "object_id": "26", "object_repr": "Summer Madness Five", "action_flag": 1, "change_message": "[{\"added\": {}}]"}}, {"model": "admin.logentry", "pk": 35, "fields": {"action_time": "2021-04-29T17:19:29.643Z", "user": 1, "content_type": 14, "object_id": "27", "object_repr": "Summer Madness Six", "action_flag": 1, "change_message": "[{\"added\": {}}]"}}, {"model": "admin.logentry", "pk": 36, "fields": {"action_time": "2021-04-29T17:20:32.588Z", "user": 1, "content_type": 14, "object_id": "28", "object_repr": "Summer Madness Eight", "action_flag": 1, "change_message": "[{\"added\": {}}]"}}, {"model": "admin.logentry", "pk": 37, "fields": {"action_time": "2021-04-29T17:21:14.510Z", "user": 1, "content_type": 14, "object_id": "29", "object_repr": "Summer Madness Nine", "action_flag": 1, "change_message": "[{\"added\": {}}]"}}, {"model": "admin.logentry", "pk": 38, "fields": {"action_time": "2021-04-29T17:21:46.675Z", "user": 1, "content_type": 14, "object_id": "28", "object_repr": "Summer Madness Seven", "action_flag": 2, "change_message": "[{\"changed\": {\"fields\": [\"Name\"]}}]"}}, {"model": "admin.logentry", "pk": 39, "fields": {"action_time": "2021-04-29T17:21:57.364Z", "user": 1, "content_type": 14, "object_id": "29", "object_repr": "Summer Madness Eight", "action_flag": 2, "change_message": "[{\"changed\": {\"fields\": [\"Name\"]}}]"}}, {"model": "admin.logentry", "pk": 40, "fields": {"action_time": "2021-04-29T17:23:16.628Z", "user": 1, "content_type": 14, "object_id": "30", "object_repr": "Hiss", "action_flag": 1, "change_message": "[{\"added\": {}}]"}}, {"model": "admin.logentry", "pk": 41, "fields": {"action_time": "2021-04-29T20:05:45.243Z", "user": 1, "content_type": 7, "object_id": "1", "object_repr": "hardman-photo.com", "action_flag": 2, "change_message": "[{\"changed\": {\"fields\": [\"Domain name\", \"Display name\"]}}]"}}, {"model": "admin.logentry", "pk": 42, "fields": {"action_time": "2021-04-29T20:05:57.651Z", "user": 1, "content_type": 7, "object_id": "1", "object_repr": "hardman-photo.com", "action_flag": 2, "change_message": "[{\"changed\": {\"fields\": [\"Display name\"]}}]"}}, {"model": "auth.user", "pk": 1, "fields": {"password": "pbkdf2_sha256$216000$JwQ4HnSPGCjY$nhPT45rO3K+JnVH5O87rvhLtfrVSnYCb2rbioSvxUaY=", "last_login": "2021-06-21T19:45:01.447Z", "is_superuser": true, "username": "superuser123", "first_name": "", "last_name": "", "email": "chardma3@hotmail.com", "is_staff": true, "is_active": true, "date_joined": "2021-04-29T11:12:13.834Z", "groups": [], "user_permissions": []}}, {"model": "sessions.session", "pk": "t3but5xha03qvq0pcgq6krfzustdlhxq", "fields": {"session_data": ".eJxVjEEOwjAMBP-SM4piJ6pbbvCRythGrahSiSQnxN9pUQ9w3NndebmRW53GVuw5zurODtzpl91YHpb3gpdlx55F1par_26OuvjLlizXWbjOa74erz_VxGXaPLFPCDEmUiINCRMqdsBBIRjTQLHHYegkAEUFQL5jEJPIIEYKou79AXcxO2U:1lvPqv:RVffquDNJ2TZNgZ1csXV24zqRpQP_c-QW5sk4nhyOHE", "expire_date": "2021-07-05T19:45:01.486Z"}}, {"model": "sessions.session", "pk": "tbm03tasqrpkk5pxg699vbhlgolboghj", "fields": {"session_data": "eyJiYWciOnsiMSI6eyJpdGVtc19ieV9zaXplIjp7IjUweDcwIjoxfX19fQ:1lcWv7:j6D4c4SAqZEfpegfS7zgDxcfW00KmGG7Imfy6CenHuU", "expire_date": "2021-05-14T17:27:17.700Z"}}, {"model": "sessions.session", "pk": "typzsyiz4vue3p8g6plgi9bhvbp6z291", "fields": {"session_data": "eyJiYWciOnsiOSI6eyJpdGVtc19ieV9zaXplIjp7ImwiOjF9fX19:1lcIEe:j7mubYzW_u13Zw8gxU7icWdCHsWWEHTlIWxbA8eU5yI", "expire_date": "2021-05-14T01:46:28.340Z"}}, {"model": "sessions.session", "pk": "x7mslm4gwd1odjd8t00frco3qa4qign5", "fields": {"session_data": ".eJxVjLEOgzAQQ_8lcxXlkogAY_d-Q3TJXSFtAYnAQFH_vURiaD148LO9C4_r0vs18-wTiVaAuPxmAeOTxwLogWM3yTiNy5yCLBV50ixvE_Hrenb_DnrM_bE2tdVgjHXkHCmrrSZdASoCxegaZ2rdNFVU4AwBaLxrFTkahMiOIJbTgJ1odwGmeFp4yD5sPqc3l2AQLXwOfQHmSkOf:1lcANg:09TLHIiZ4Osk6eJAOlxvY8X_dACVPZluFeECnFwN08Y", "expire_date": "2021-05-13T17:23:16.811Z"}}, {"model": "sites.site", "pk": 1, "fields": {"domain": "hardman-photo.com", "name": "Hardman Photo"}}, {"model": "products.category", "pk": 1, "fields": {"name": "portraits", "friendly_name": "Portraits"}}, {"model": "products.category", "pk": 2, "fields": {"name": "b_w", "friendly_name": "B+W"}}, {"model": "products.category", "pk": 3, "fields": {"name": "collage", "friendly_name": "Collage"}}, {"model": "products.category", "pk": 4, "fields": {"name": "urban", "friendly_name": "Urban"}}, {"model": "products.category", "pk": 5, "fields": {"name": "new", "friendly_name": "New Collection"}}, {"model": "products.product", "pk": 1, "fields": {"category": 1, "name": "Chesterfield", "has_sizes": true, "price": "100.00", "image_url": null, "image": "chesterfield_7skXI4I.jpg"}}, {"model": "products.product", "pk": 2, "fields": {"category": 1, "name": "Sandstone", "has_sizes": true, "price": "75.00", "image_url": null, "image": "sjosdedt4.jpg"}}, {"model": "products.product", "pk": 3, "fields": {"category": 1, "name": "Lace", "has_sizes": true, "price": "80.00", "image_url": null, "image": "seanbradford5.jpg"}}, {"model": "products.product", "pk": 4, "fields": {"category": 1, "name": "Winter", "has_sizes": true, "price": "120.00", "image_url": null, "image": "noemi_9.jpg"}}, {"model": "products.product", "pk": 5, "fields": {"category": 2, "name": "Mongolian", "has_sizes": true, "price": "65.00", "image_url": null, "image": "mongolian14.jpg"}}, {"model": "products.product", "pk": 6, "fields": {"category": 2, "name": "Rain", "has_sizes": true, "price": "80.00", "image_url": null, "image": "harrow23_jnSVwYZ.jpg"}}, {"model": "products.product", "pk": 7, "fields": {"category": 2, "name": "Recital", "has_sizes": true, "price": "90.00", "image_url": null, "image": "harrow21.jpg"}}, {"model": "products.product", "pk": 8, "fields": {"category": 2, "name": "Martin", "has_sizes": true, "price": "100.00", "image_url": null, "image": "martinbarra4_J03iM80.jpg"}}, {"model": "products.product", "pk": 9, "fields": {"category": 3, "name": "Dreams", "has_sizes": true, "price": "100.00", "image_url": null, "image": "copenhagen40_Sz13QYd.jpg"}}, {"model": "products.product", "pk": 10, "fields": {"category": 3, "name": "Carusel", "has_sizes": true, "price": "120.00", "image_url": null, "image": "copenhagen39_UAxTlua.jpg"}}, {"model": "products.product", "pk": 11, "fields": {"category": 4, "name": "Middle", "has_sizes": true, "price": "70.00", "image_url": null, "image": "copenhagen14_8Ix5d4Z.jpg"}}, {"model": "products.product", "pk": 12, "fields": {"category": 3, "name": "Gods", "has_sizes": true, "price": "110.00", "image_url": null, "image": "copenhagen13_FqdnLU0.jpg"}}, {"model": "products.product", "pk": 13, "fields": {"category": 5, "name": "Shoes", "has_sizes": true, "price": "90.00", "image_url": null, "image": "androgynous7_LbTBNym.jpg"}}, {"model": "products.product", "pk": 14, "fields": {"category": 5, "name": "Below", "has_sizes": true, "price": "110.00", "image_url": null, "image": "androgynous3_PfxqVKm.jpg"}}, {"model": "products.product", "pk": 15, "fields": {"category": 5, "name": "Burden", "has_sizes": true, "price": "95.00", "image_url": null, "image": "androgynous4_xnK9X5K.jpg"}}, {"model": "products.product", "pk": 16, "fields": {"category": 5, "name": "Him", "has_sizes": true, "price": "100.00", "image_url": null, "image": "androgynous6_ZfsNea6.jpg"}}, {"model": "products.product", "pk": 17, "fields": {"category": 5, "name": "Her", "has_sizes": true, "price": "100.00", "image_url": null, "image": "androgynous5_EytxghG.jpg"}}, {"model": "products.product", "pk": 18, "fields": {"category": 4, "name": "Bikes", "has_sizes": true, "price": "80.00", "image_url": null, "image": "copenhagen5.jpg"}}, {"model": "products.product", "pk": 19, "fields": {"category": 4, "name": "Light", "has_sizes": true, "price": "80.00", "image_url": null, "image": "copenhagen16_1PShFua.jpg"}}, {"model": "products.product", "pk": 20, "fields": {"category": 3, "name": "Daily", "has_sizes": true, "price": "85.00", "image_url": null, "image": "copenhagen25_imtcXQL.jpg"}}, {"model": "products.product", "pk": 21, "fields": {"category": 4, "name": "Ekstra", "has_sizes": true, "price": "80.00", "image_url": null, "image": "copenhagen15_VfAEIJg.jpg"}}, {"model": "products.product", "pk": 22, "fields": {"category": 1, "name": "Summer Madness One", "has_sizes": true, "price": "250.00", "image_url": null, "image": "summermadness1_TfO2XqY.jpg"}}, {"model": "products.product", "pk": 23, "fields": {"category": 1, "name": "Summer Madness Two", "has_sizes": true, "price": "250.00", "image_url": null, "image": "summermadness2_0hmBhhp.jpg"}}, {"model": "products.product", "pk": 24, "fields": {"category": 1, "name": "Summer Madness Three", "has_sizes": true, "price": "250.00", "image_url": null, "image": "summermadness3_81o5Cad.jpg"}}, {"model": "products.product", "pk": 25, "fields": {"category": 1, "name": "Summer Madness Four", "has_sizes": true, "price": "250.00", "image_url": null, "image": "summermadness4_T2r8owy.jpg"}}, {"model": "products.product", "pk": 26, "fields": {"category": 1, "name": "Summer Madness Five", "has_sizes": true, "price": "250.00", "image_url": null, "image": "summermadness6_tClWAW0.jpg"}}, {"model": "products.product", "pk": 27, "fields": {"category": 1, "name": "Summer Madness Six", "has_sizes": true, "price": "250.00", "image_url": null, "image": "summermadness7_DAF9CZ5.jpg"}}, {"model": "products.product", "pk": 28, "fields": {"category": 1, "name": "Summer Madness Seven", "has_sizes": true, "price": "250.00", "image_url": null, "image": "summermadness9_OozSEHB.jpg"}}, {"model": "products.product", "pk": 29, "fields": {"category": 1, "name": "Summer Madness Eight", "has_sizes": true, "price": "250.00", "image_url": null, "image": "summermadness10_B1WFCAU.jpg"}}, {"model": "products.product", "pk": 30, "fields": {"category": 1, "name": "Hiss", "has_sizes": true, "price": "200.00", "image_url": null, "image": "martinbarra1_3K4vP4J.jpg"}}, {"model": "profiles.userprofile", "pk": 1, "fields": {"user": 1, "default_phone_number": null, "default_street_address1": null, "default_street_address2": null, "default_town_or_city": null, "default_county": null, "default_postcode": null, "default_country": null}}]